mypassman-2.0.0.dist-info/METADATA
mypassman-2.0.0.dist-info/RECORD
mypassman-2.0.0.dist-info/WHEEL
mypassman-2.0.0.dist-info/entry_points.txt
mypassman-2.0.0.dist-info/top_level.txt
passman/__init__.py
passman/passman.py
