Metadata-Version: 2.1
Name: mypassman
Version: 2.0.0
Summary: A super simple password management app
Home-page: https://github.com/seanpierce/passman
Author: Sean Pierce
Author-email: sumler.sean@gmail.com
License: UNKNOWN
Platform: UNKNOWN
Classifier: Programming Language :: Python :: 3
Classifier: License :: OSI Approved :: MIT License
Classifier: Operating System :: OS Independent
Classifier: Topic :: Utilities
